{
	"2089": {
		"File": "main.c",
		"Line": 234
	},
	"3996": {
		"File": "main.c",
		"Line": 190
	},
	"4528": {
		"File": "main.c",
		"Line": 163
	},
	"4877": {
		"File": "main.c",
		"Line": 163
	},
	"5065": {
		"File": "main.c",
		"Line": 190
	},
	"5676": {
		"File": "main.c",
		"Line": 162
	},
	"6226": {
		"File": "main.c",
		"Line": 234
	},
	"6959": {
		"File": "main.c",
		"Line": 172
	},
	"7167": {
		"File": "main.c",
		"Line": 127
	},
	"7369": {
		"File": "main.c",
		"Line": 185
	},
	"7750": {
		"File": "main.c",
		"Line": 176
	}
}